json_schema_for_humans/__init__.py
json_schema_for_humans/cli.py
json_schema_for_humans/const.py
json_schema_for_humans/generate.py
json_schema_for_humans/generation_configuration.py
json_schema_for_humans/jinja_filters.py
json_schema_for_humans/md_template.py
json_schema_for_humans/schema/__init__.py
json_schema_for_humans/schema/intermediate_representation.py
json_schema_for_humans/schema/schema_importer.py
json_schema_for_humans/schema/schema_keyword.py
json_schema_for_humans/schema/schema_node.py
json_schema_for_humans/schema/schema_to_render.py
json_schema_for_humans/template_renderer.py
json_schema_for_humans/templates/flat/badge_type.html
json_schema_for_humans/templates/flat/base.html
json_schema_for_humans/templates/flat/breadcrumbs.html
json_schema_for_humans/templates/flat/content.html
json_schema_for_humans/templates/flat/macro_restriction.html
json_schema_for_humans/templates/flat/schema_doc.css
json_schema_for_humans/templates/flat/section_array.html
json_schema_for_humans/templates/flat/section_conditional_subschema.html
json_schema_for_humans/templates/flat/section_description.html
json_schema_for_humans/templates/flat/section_examples.html
json_schema_for_humans/templates/flat/section_not.html
json_schema_for_humans/templates/flat/section_properties.html
json_schema_for_humans/templates/flat/section_undocumented_required_properties.html
json_schema_for_humans/templates/flat/tabbed_section.html
json_schema_for_humans/templates/js/badge_type.html
json_schema_for_humans/templates/js/base.html
json_schema_for_humans/templates/js/breadcrumbs.html
json_schema_for_humans/templates/js/content.html
json_schema_for_humans/templates/js/macro_restriction.html
json_schema_for_humans/templates/js/schema_doc.css
json_schema_for_humans/templates/js/schema_doc.js
json_schema_for_humans/templates/js/schema_doc.min.js
json_schema_for_humans/templates/js/section_array.html
json_schema_for_humans/templates/js/section_conditional_subschema.html
json_schema_for_humans-1.4.1.dist-info/LICENSE.md
json_schema_for_humans-1.4.1.dist-info/METADATA
json_schema_for_humans-1.4.1.dist-info/WHEEL
json_schema_for_humans-1.4.1.dist-info/entry_points.txt
json_schema_for_humans-1.4.1.dist-info/RECORD
