Metadata-Version: 2.3
Name: json-schema-for-humans
Version: 1.4.1
Summary: Generate static HTML documentation from JSON schemas
License: Apache-2.0
Author: Denis Blanchette
Author-email: tools@coveo.com
Requires-Python: >=3.9,<4.0
Classifier: Development Status :: 6 - Mature
Classifier: Intended Audience :: Developers
Classifier: License :: OSI Approved :: Apache Software License
Classifier: Operating System :: OS Independent
Classifier: Programming Language :: Python :: 3
Classifier: Programming Language :: Python :: 3.9
Classifier: Programming Language :: Python :: 3.10
Classifier: Programming Language :: Python :: 3.11
Classifier: Programming Language :: Python :: 3.12
Classifier: Programming Language :: Python :: 3.13
Classifier: Topic :: Documentation
Requires-Dist: Jinja2 (>3)
Requires-Dist: PyYAML (>=6.0.2,<7.0.0)
Requires-Dist: Pygments (>=2.18.0,<3.0.0)
Requires-Dist: click (>=8.0.1,<9.0.0)
Requires-Dist: dataclasses-json (>=0.6.7,<0.7.0)
Requires-Dist: markdown2 (>=2.5.0,<3.0.0)
Requires-Dist: pytz
Requires-Dist: requests (>=2.32.3,<3.0.0)
Project-URL: Repository, https://github.com/coveooss/json-schema-for-humans
